long_gen/__init__.py
long_gen-0.1.6.dist-info/LICENSE.md
long_gen-0.1.6.dist-info/METADATA
long_gen-0.1.6.dist-info/WHEEL
long_gen-0.1.6.dist-info/top_level.txt
long_gen-0.1.6.dist-info/RECORD
