Metadata-Version: 2.1
Name: long-gen
Version: 0.1.6
Summary: A library of functions for generating longitudinal data
Home-page: https://github.com/matthew-c-lenert/Long-Gen
Author: MC Lenert
Author-email: matthew.c.lenert@gmail.com
License: MIT
Keywords: generate data longitudinal time series synthetic
Platform: UNKNOWN
Classifier: Development Status :: 4 - Beta
Classifier: License :: OSI Approved :: MIT License
Classifier: Programming Language :: Python :: 3.6
Classifier: Topic :: Scientific/Engineering :: Information Analysis
Classifier: Topic :: Scientific/Engineering :: Medical Science Apps.
Requires-Dist: numpy
Requires-Dist: pandas
Requires-Dist: sklearn
Requires-Dist: scipy
